{"name":"Automatic registration","id":"utest;automatic-registration","testSteps":[{"number":1,"description":"Given that Mauricio wanted to register on the UTest platform","duration":28311,"startTime":"2021-11-16T08:25:17.238315500-05:00[America/Bogota]","screenshots":[{"screenshot":"9c5f071f51e69289c761083b1f372c5c7c28f4af8ac62e2e0dbdf687ac587f18.png","timeStamp":1637069145549}],"result":"SUCCESS","precondition":false,"level":0,"lineNumber":0,"children":[{"number":2,"description":"Mauricio open up","duration":25241,"startTime":"2021-11-16T08:25:19.567758400-05:00[America/Bogota]","screenshots":[{"screenshot":"9c5f071f51e69289c761083b1f372c5c7c28f4af8ac62e2e0dbdf687ac587f18.png","timeStamp":1637069144809}],"result":"SUCCESS","precondition":false,"level":1,"lineNumber":0,"children":[{"number":3,"description":"Mauricio opens the U test page","duration":24395,"startTime":"2021-11-16T08:25:19.642788400-05:00[America/Bogota]","screenshots":[{"screenshot":"9c5f071f51e69289c761083b1f372c5c7c28f4af8ac62e2e0dbdf687ac587f18.png","timeStamp":1637069144037}],"result":"SUCCESS","precondition":false,"level":2,"lineNumber":0}]}]},{"number":4,"description":"When you enter the data requested for registration","duration":61260,"startTime":"2021-11-16T08:25:45.556654100-05:00[America/Bogota]","exception":{"errorType":"net.thucydides.core.webdriver.exceptions.ElementShouldBeEnabledException","message":"Expected enabled element was not enabled","stackTrace":[{"classLoaderName":"app","declaringClass":"co.com.dmvs.proyecto.task.StepComplete","methodName":"performAs","fileName":"StepComplete.java","lineNumber":20,"format":1},{"classLoaderName":"app","declaringClass":"co.com.dmvs.proyecto.stepdefinitions.ChourcairAcademyStepDefinitions","methodName":"youEnterTheDataRequestedForRegistration","fileName":"ChourcairAcademyStepDefinitions.java","lineNumber":27,"format":1},{"classLoaderName":"app","declaringClass":"cucumber.runner.Runner","methodName":"runPickle","fileName":"Runner.java","lineNumber":80,"format":1}],"rootCause":{"errorType":"org.openqa.selenium.TimeoutException","message":"Expected condition failed: waiting for By.xpath: //label[contains(@class,\u0027checkmark signup-consent__checkbox error\u0027)] to be enabled (tried for 5 second(s) with 100 milliseconds interval)","stackTrace":[{"classLoaderName":"app","declaringClass":"co.com.dmvs.proyecto.task.StepComplete","methodName":"performAs","fileName":"StepComplete.java","lineNumber":20,"format":1},{"classLoaderName":"app","declaringClass":"co.com.dmvs.proyecto.stepdefinitions.ChourcairAcademyStepDefinitions","methodName":"youEnterTheDataRequestedForRegistration","fileName":"ChourcairAcademyStepDefinitions.java","lineNumber":27,"format":1},{"classLoaderName":"app","declaringClass":"cucumber.runner.Runner","methodName":"runPickle","fileName":"Runner.java","lineNumber":80,"format":1}],"rootCause":{"errorType":"org.openqa.selenium.NoSuchElementException","message":"no such element: Unable to locate element: {\"method\":\"xpath\",\"selector\":\"//label[contains(@class,\u0027checkmark signup-consent__checkbox error\u0027)]\"}\n  (Session info: chrome\u003d95.0.4638.69)\nFor documentation on this error, please visit: https://www.seleniumhq.org/exceptions/no_such_element.html\nBuild info: version: \u00273.141.59\u0027, revision: \u0027e82be7d358\u0027, time: \u00272018-11-14T08:17:03\u0027\nSystem info: host: \u0027SISTEMAS\u0027, ip: \u0027172.20.208.1\u0027, os.name: \u0027Windows 10\u0027, os.arch: \u0027amd64\u0027, os.version: \u002710.0\u0027, java.version: \u002711.0.4\u0027\nDriver info: org.openqa.selenium.chrome.ChromeDriver\nCapabilities {acceptInsecureCerts: false, browserName: chrome, browserVersion: 95.0.4638.69, chrome: {chromedriverVersion: 95.0.4638.69 (6a1600ed572fe..., userDataDir: C:\\Users\\Sistemas\\AppData\\L...}, goog:chromeOptions: {debuggerAddress: localhost:52374}, javascriptEnabled: true, networkConnectionEnabled: false, pageLoadStrategy: normal, platform: WINDOWS, platformName: WINDOWS, proxy: Proxy(), setWindowRect: true, strictFileInteractability: false, timeouts: {implicit: 0, pageLoad: 300000, script: 30000}, unhandledPromptBehavior: dismiss and notify, webauthn:extension:credBlob: true, webauthn:extension:largeBlob: true, webauthn:virtualAuthenticators: true}\nSession ID: 406359d0b7d2bfbe3a11cd9b1ba20110\n*** Element info: {Using\u003dxpath, value\u003d//label[contains(@class,\u0027checkmark signup-consent__checkbox error\u0027)]}","stackTrace":[{"classLoaderName":"app","declaringClass":"co.com.dmvs.proyecto.task.StepComplete","methodName":"performAs","fileName":"StepComplete.java","lineNumber":20,"format":1},{"classLoaderName":"app","declaringClass":"co.com.dmvs.proyecto.stepdefinitions.ChourcairAcademyStepDefinitions","methodName":"youEnterTheDataRequestedForRegistration","fileName":"ChourcairAcademyStepDefinitions.java","lineNumber":27,"format":1},{"classLoaderName":"app","declaringClass":"cucumber.runner.Runner","methodName":"runPickle","fileName":"Runner.java","lineNumber":80,"format":1}]}}},"result":"FAILURE","precondition":false,"level":0,"lineNumber":0,"children":[{"number":5,"description":"Mauricio step personal","duration":25055,"startTime":"2021-11-16T08:25:45.664653-05:00[America/Bogota]","screenshots":[{"screenshot":"709a9e52474e248df54a613de4a477d40b1cb965962e54eec52a34c8b0c5a74d.png","timeStamp":1637069170720}],"result":"SUCCESS","precondition":false,"level":1,"lineNumber":0,"children":[{"number":6,"description":"Mauricio clicks on button that shows us the form to register","duration":2586,"startTime":"2021-11-16T08:25:46.153145400-05:00[America/Bogota]","screenshots":[{"screenshot":"1a744ec42b4eec6ce24a1e3292be4c9a86a1363c5f61955795858b347f213d42.png","timeStamp":1637069148740}],"result":"SUCCESS","precondition":false,"level":2,"lineNumber":0},{"number":7,"description":"Mauricio enters \u0027Quest\u0027 into where we write the first name","duration":5609,"startTime":"2021-11-16T08:25:48.757146800-05:00[America/Bogota]","screenshots":[{"screenshot":"4b3a4a93405c4260a8c449dc2628921ea76e2f28c461c0a4b294b99ea24bd03c.png","timeStamp":1637069154367}],"result":"SUCCESS","precondition":false,"level":2,"lineNumber":0},{"number":8,"description":"Mauricio enters \u0027Legends\u0027 into where we write the last name","duration":2444,"startTime":"2021-11-16T08:25:54.377031900-05:00[America/Bogota]","screenshots":[{"screenshot":"c1ee36d77cf9b58eb019169e456ca847d5c71f527f01f64d80c66e9175baab2f.png","timeStamp":1637069156821}],"result":"SUCCESS","precondition":false,"level":2,"lineNumber":0},{"number":9,"description":"Mauricio enters \u0027qlegends@hotmail.com\u0027 into where we write the email address","duration":2639,"startTime":"2021-11-16T08:25:56.836741-05:00[America/Bogota]","screenshots":[{"screenshot":"4bb7ae5210529d765a234215ddf0315e4c414faac1ff3cfbfcae71c8b8d5cc0a.png","timeStamp":1637069159474}],"result":"SUCCESS","precondition":false,"level":2,"lineNumber":0},{"number":10,"description":"Mauricio selects index 12 in where we select the month of the birthday date","duration":2510,"startTime":"2021-11-16T08:25:59.483156-05:00[America/Bogota]","screenshots":[{"screenshot":"02ea5277e81f0bc2aa2ba43f1287d3026d2fb5d046815f31f0bea71fba6dcda7.png","timeStamp":1637069161992}],"result":"SUCCESS","precondition":false,"level":2,"lineNumber":0},{"number":11,"description":"Mauricio selects index 31 in where we select the day of the birthday date","duration":3389,"startTime":"2021-11-16T08:26:01.998156500-05:00[America/Bogota]","screenshots":[{"screenshot":"2caa310094dad7c54a75124e7aa57e60ea8d75ef9403391c7f50d0c0aa714d87.png","timeStamp":1637069165387}],"result":"SUCCESS","precondition":false,"level":2,"lineNumber":0},{"number":12,"description":"Mauricio selects index 11 in where we select the year of the birthday date","duration":2514,"startTime":"2021-11-16T08:26:05.390187300-05:00[America/Bogota]","screenshots":[{"screenshot":"9d6a756a533bde8c9fe761792912b445a068fc27806a22738fe7a483ee5b0ba5.png","timeStamp":1637069167904}],"result":"SUCCESS","precondition":false,"level":2,"lineNumber":0},{"number":13,"description":"Mauricio clicks on button to next page location","duration":2777,"startTime":"2021-11-16T08:26:07.908186300-05:00[America/Bogota]","screenshots":[{"screenshot":"709a9e52474e248df54a613de4a477d40b1cb965962e54eec52a34c8b0c5a74d.png","timeStamp":1637069170684}],"result":"SUCCESS","precondition":false,"level":2,"lineNumber":0}]},{"number":14,"description":"Mauricio step address","duration":11644,"startTime":"2021-11-16T08:26:10.723185500-05:00[America/Bogota]","screenshots":[{"screenshot":"91bec5d0c2980905dbd74c949f808eb98c7c3915fafeef21c59e939095e5aba7.png","timeStamp":1637069182367}],"result":"SUCCESS","precondition":false,"level":1,"lineNumber":0,"children":[{"number":15,"description":"Mauricio enters \u0027Cali\u0027 into where we write the city","duration":3503,"startTime":"2021-11-16T08:26:10.961188200-05:00[America/Bogota]","screenshots":[{"screenshot":"c2c19247849ee380833e3e2031e3cf7ff8106771312e8856892cb64c2df62a35.png","timeStamp":1637069174465}],"result":"SUCCESS","precondition":false,"level":2,"lineNumber":0},{"number":16,"description":"Mauricio enters \u0027760042\u0027 into where we write the number zip or postal code","duration":3146,"startTime":"2021-11-16T08:26:14.473198900-05:00[America/Bogota]","screenshots":[{"screenshot":"53985dc9dd403e79dcf7fd3d0c226a7c9b946d11d9e3bdae30a0250a3bfb8dbf.png","timeStamp":1637069177620}],"result":"SUCCESS","precondition":false,"level":2,"lineNumber":0},{"number":17,"description":"Mauricio clicks on button to next page location","duration":4700,"startTime":"2021-11-16T08:26:17.625154500-05:00[America/Bogota]","screenshots":[{"screenshot":"91bec5d0c2980905dbd74c949f808eb98c7c3915fafeef21c59e939095e5aba7.png","timeStamp":1637069182325}],"result":"SUCCESS","precondition":false,"level":2,"lineNumber":0}]},{"number":18,"description":"Mauricio step devices","duration":5932,"startTime":"2021-11-16T08:26:22.370856100-05:00[America/Bogota]","screenshots":[{"screenshot":"b55433ae9f198968f02f268d875507eed4d540d9e3398c13a2996ac0b4f1c8f2.png","timeStamp":1637069188302}],"result":"SUCCESS","precondition":false,"level":1,"lineNumber":0,"children":[{"number":19,"description":"Mauricio clicks on button to next page location","duration":3721,"startTime":"2021-11-16T08:26:22.406854800-05:00[America/Bogota]","screenshots":[{"screenshot":"8ca314c7b4dbe2e920ac70e3bfbf980828442f8c06bf0e70ef86866e05a6626f.png","timeStamp":1637069186127}],"result":"SUCCESS","precondition":false,"level":2,"lineNumber":0}]},{"number":20,"description":"Mauricio step complete","duration":18458,"startTime":"2021-11-16T08:26:28.307857500-05:00[America/Bogota]","exception":{"errorType":"net.thucydides.core.webdriver.exceptions.ElementShouldBeEnabledException","message":"Expected enabled element was not enabled","stackTrace":[{"classLoaderName":"app","declaringClass":"co.com.dmvs.proyecto.task.StepComplete","methodName":"performAs","fileName":"StepComplete.java","lineNumber":20,"format":1},{"classLoaderName":"app","declaringClass":"co.com.dmvs.proyecto.stepdefinitions.ChourcairAcademyStepDefinitions","methodName":"youEnterTheDataRequestedForRegistration","fileName":"ChourcairAcademyStepDefinitions.java","lineNumber":27,"format":1},{"classLoaderName":"app","declaringClass":"cucumber.runner.Runner","methodName":"runPickle","fileName":"Runner.java","lineNumber":80,"format":1}],"rootCause":{"errorType":"org.openqa.selenium.TimeoutException","message":"Expected condition failed: waiting for By.xpath: //label[contains(@class,\u0027checkmark signup-consent__checkbox error\u0027)] to be enabled (tried for 5 second(s) with 100 milliseconds interval)","stackTrace":[{"classLoaderName":"app","declaringClass":"co.com.dmvs.proyecto.task.StepComplete","methodName":"performAs","fileName":"StepComplete.java","lineNumber":20,"format":1},{"classLoaderName":"app","declaringClass":"co.com.dmvs.proyecto.stepdefinitions.ChourcairAcademyStepDefinitions","methodName":"youEnterTheDataRequestedForRegistration","fileName":"ChourcairAcademyStepDefinitions.java","lineNumber":27,"format":1},{"classLoaderName":"app","declaringClass":"cucumber.runner.Runner","methodName":"runPickle","fileName":"Runner.java","lineNumber":80,"format":1}],"rootCause":{"errorType":"org.openqa.selenium.NoSuchElementException","message":"no such element: Unable to locate element: {\"method\":\"xpath\",\"selector\":\"//label[contains(@class,\u0027checkmark signup-consent__checkbox error\u0027)]\"}\n  (Session info: chrome\u003d95.0.4638.69)\nFor documentation on this error, please visit: https://www.seleniumhq.org/exceptions/no_such_element.html\nBuild info: version: \u00273.141.59\u0027, revision: \u0027e82be7d358\u0027, time: \u00272018-11-14T08:17:03\u0027\nSystem info: host: \u0027SISTEMAS\u0027, ip: \u0027172.20.208.1\u0027, os.name: \u0027Windows 10\u0027, os.arch: \u0027amd64\u0027, os.version: \u002710.0\u0027, java.version: \u002711.0.4\u0027\nDriver info: org.openqa.selenium.chrome.ChromeDriver\nCapabilities {acceptInsecureCerts: false, browserName: chrome, browserVersion: 95.0.4638.69, chrome: {chromedriverVersion: 95.0.4638.69 (6a1600ed572fe..., userDataDir: C:\\Users\\Sistemas\\AppData\\L...}, goog:chromeOptions: {debuggerAddress: localhost:52374}, javascriptEnabled: true, networkConnectionEnabled: false, pageLoadStrategy: normal, platform: WINDOWS, platformName: WINDOWS, proxy: Proxy(), setWindowRect: true, strictFileInteractability: false, timeouts: {implicit: 0, pageLoad: 300000, script: 30000}, unhandledPromptBehavior: dismiss and notify, webauthn:extension:credBlob: true, webauthn:extension:largeBlob: true, webauthn:virtualAuthenticators: true}\nSession ID: 406359d0b7d2bfbe3a11cd9b1ba20110\n*** Element info: {Using\u003dxpath, value\u003d//label[contains(@class,\u0027checkmark signup-consent__checkbox error\u0027)]}","stackTrace":[{"classLoaderName":"app","declaringClass":"co.com.dmvs.proyecto.task.StepComplete","methodName":"performAs","fileName":"StepComplete.java","lineNumber":20,"format":1},{"classLoaderName":"app","declaringClass":"co.com.dmvs.proyecto.stepdefinitions.ChourcairAcademyStepDefinitions","methodName":"youEnterTheDataRequestedForRegistration","fileName":"ChourcairAcademyStepDefinitions.java","lineNumber":27,"format":1},{"classLoaderName":"app","declaringClass":"cucumber.runner.Runner","methodName":"runPickle","fileName":"Runner.java","lineNumber":80,"format":1}]}}},"result":"FAILURE","precondition":false,"level":1,"lineNumber":0,"children":[{"number":21,"description":"Mauricio enters \u002762lR3sthdNcz\u0027 into where we write the first name","duration":3353,"startTime":"2021-11-16T08:26:28.504866600-05:00[America/Bogota]","screenshots":[{"screenshot":"30a178b5a631688f7ce54eea186137f16dfbec517819b3e586e3dc23721b9e73.png","timeStamp":1637069191856}],"result":"SUCCESS","precondition":false,"level":2,"lineNumber":0},{"number":22,"description":"Mauricio enters \u002762lR3sthdNcz\u0027 into where we write the first name","duration":2839,"startTime":"2021-11-16T08:26:31.863855600-05:00[America/Bogota]","screenshots":[{"screenshot":"7c07203cc3dd4f57d915a908ba6ba6c8c928f7eb6992b7840b6b08ab8f0d0d29.png","timeStamp":1637069194703}],"result":"SUCCESS","precondition":false,"level":2,"lineNumber":0},{"number":23,"description":"Mauricio clicks on button to next page location","duration":12007,"startTime":"2021-11-16T08:26:34.706863900-05:00[America/Bogota]","screenshots":[{"screenshot":"7c07203cc3dd4f57d915a908ba6ba6c8c928f7eb6992b7840b6b08ab8f0d0d29.png","htmlSource":"pagesource10147070768651609005.html.txt","timeStamp":1637069206697}],"exception":{"errorType":"net.thucydides.core.webdriver.exceptions.ElementShouldBeEnabledException","message":"Expected enabled element was not enabled","stackTrace":[{"classLoaderName":"app","declaringClass":"co.com.dmvs.proyecto.task.StepComplete","methodName":"performAs","fileName":"StepComplete.java","lineNumber":20,"format":1},{"classLoaderName":"app","declaringClass":"co.com.dmvs.proyecto.stepdefinitions.ChourcairAcademyStepDefinitions","methodName":"youEnterTheDataRequestedForRegistration","fileName":"ChourcairAcademyStepDefinitions.java","lineNumber":27,"format":1},{"classLoaderName":"app","declaringClass":"cucumber.runner.Runner","methodName":"runPickle","fileName":"Runner.java","lineNumber":80,"format":1}],"rootCause":{"errorType":"org.openqa.selenium.TimeoutException","message":"Expected condition failed: waiting for By.xpath: //label[contains(@class,\u0027checkmark signup-consent__checkbox error\u0027)] to be enabled (tried for 5 second(s) with 100 milliseconds interval)","stackTrace":[{"classLoaderName":"app","declaringClass":"co.com.dmvs.proyecto.task.StepComplete","methodName":"performAs","fileName":"StepComplete.java","lineNumber":20,"format":1},{"classLoaderName":"app","declaringClass":"co.com.dmvs.proyecto.stepdefinitions.ChourcairAcademyStepDefinitions","methodName":"youEnterTheDataRequestedForRegistration","fileName":"ChourcairAcademyStepDefinitions.java","lineNumber":27,"format":1},{"classLoaderName":"app","declaringClass":"cucumber.runner.Runner","methodName":"runPickle","fileName":"Runner.java","lineNumber":80,"format":1}],"rootCause":{"errorType":"org.openqa.selenium.NoSuchElementException","message":"no such element: Unable to locate element: {\"method\":\"xpath\",\"selector\":\"//label[contains(@class,\u0027checkmark signup-consent__checkbox error\u0027)]\"}\n  (Session info: chrome\u003d95.0.4638.69)\nFor documentation on this error, please visit: https://www.seleniumhq.org/exceptions/no_such_element.html\nBuild info: version: \u00273.141.59\u0027, revision: \u0027e82be7d358\u0027, time: \u00272018-11-14T08:17:03\u0027\nSystem info: host: \u0027SISTEMAS\u0027, ip: \u0027172.20.208.1\u0027, os.name: \u0027Windows 10\u0027, os.arch: \u0027amd64\u0027, os.version: \u002710.0\u0027, java.version: \u002711.0.4\u0027\nDriver info: org.openqa.selenium.chrome.ChromeDriver\nCapabilities {acceptInsecureCerts: false, browserName: chrome, browserVersion: 95.0.4638.69, chrome: {chromedriverVersion: 95.0.4638.69 (6a1600ed572fe..., userDataDir: C:\\Users\\Sistemas\\AppData\\L...}, goog:chromeOptions: {debuggerAddress: localhost:52374}, javascriptEnabled: true, networkConnectionEnabled: false, pageLoadStrategy: normal, platform: WINDOWS, platformName: WINDOWS, proxy: Proxy(), setWindowRect: true, strictFileInteractability: false, timeouts: {implicit: 0, pageLoad: 300000, script: 30000}, unhandledPromptBehavior: dismiss and notify, webauthn:extension:credBlob: true, webauthn:extension:largeBlob: true, webauthn:virtualAuthenticators: true}\nSession ID: 406359d0b7d2bfbe3a11cd9b1ba20110\n*** Element info: {Using\u003dxpath, value\u003d//label[contains(@class,\u0027checkmark signup-consent__checkbox error\u0027)]}","stackTrace":[{"classLoaderName":"app","declaringClass":"co.com.dmvs.proyecto.task.StepComplete","methodName":"performAs","fileName":"StepComplete.java","lineNumber":20,"format":1},{"classLoaderName":"app","declaringClass":"co.com.dmvs.proyecto.stepdefinitions.ChourcairAcademyStepDefinitions","methodName":"youEnterTheDataRequestedForRegistration","fileName":"ChourcairAcademyStepDefinitions.java","lineNumber":27,"format":1},{"classLoaderName":"app","declaringClass":"cucumber.runner.Runner","methodName":"runPickle","fileName":"Runner.java","lineNumber":80,"format":1}]}}},"result":"FAILURE","precondition":false,"level":2,"lineNumber":0}]}]},{"number":24,"description":"Then enter the passwords, accept terms and conditions and complete the registration","duration":13,"startTime":"2021-11-16T08:26:46.915446700-05:00[America/Bogota]","result":"SKIPPED","precondition":false,"level":0,"lineNumber":0}],"userStory":{"id":"utest","storyName":"UTest","path":"src/test/resources/features/academyChourcair.feature","narrative":"  As a user, I want to register on the UTest platform.","type":"feature"},"featureTag":{"name":"Features/UTest","type":"feature","displayName":"Features/UTest"},"title":"Automatic registration","tags":[{"name":"scenario1","type":"tag","displayName":"scenario1"},{"name":"UTest","type":"feature","displayName":"UTest"},{"name":"stories","type":"tag","displayName":"stories"}],"startTime":"2021-11-16T08:25:16.718178200-05:00[America/Bogota]","duration":90229,"testFailureCause":{"errorType":"net.thucydides.core.webdriver.exceptions.ElementShouldBeEnabledException","message":"Expected enabled element was not enabled","stackTrace":[{"classLoaderName":"app","declaringClass":"co.com.dmvs.proyecto.task.StepComplete","methodName":"performAs","fileName":"StepComplete.java","lineNumber":20,"format":1},{"classLoaderName":"app","declaringClass":"co.com.dmvs.proyecto.stepdefinitions.ChourcairAcademyStepDefinitions","methodName":"youEnterTheDataRequestedForRegistration","fileName":"ChourcairAcademyStepDefinitions.java","lineNumber":27,"format":1},{"classLoaderName":"app","declaringClass":"cucumber.runner.Runner","methodName":"runPickle","fileName":"Runner.java","lineNumber":80,"format":1}],"rootCause":{"errorType":"org.openqa.selenium.TimeoutException","message":"Expected condition failed: waiting for By.xpath: //label[contains(@class,\u0027checkmark signup-consent__checkbox error\u0027)] to be enabled (tried for 5 second(s) with 100 milliseconds interval)","stackTrace":[{"classLoaderName":"app","declaringClass":"co.com.dmvs.proyecto.task.StepComplete","methodName":"performAs","fileName":"StepComplete.java","lineNumber":20,"format":1},{"classLoaderName":"app","declaringClass":"co.com.dmvs.proyecto.stepdefinitions.ChourcairAcademyStepDefinitions","methodName":"youEnterTheDataRequestedForRegistration","fileName":"ChourcairAcademyStepDefinitions.java","lineNumber":27,"format":1},{"classLoaderName":"app","declaringClass":"cucumber.runner.Runner","methodName":"runPickle","fileName":"Runner.java","lineNumber":80,"format":1}],"rootCause":{"errorType":"org.openqa.selenium.NoSuchElementException","message":"no such element: Unable to locate element: {\"method\":\"xpath\",\"selector\":\"//label[contains(@class,\u0027checkmark signup-consent__checkbox error\u0027)]\"}\n  (Session info: chrome\u003d95.0.4638.69)\nFor documentation on this error, please visit: https://www.seleniumhq.org/exceptions/no_such_element.html\nBuild info: version: \u00273.141.59\u0027, revision: \u0027e82be7d358\u0027, time: \u00272018-11-14T08:17:03\u0027\nSystem info: host: \u0027SISTEMAS\u0027, ip: \u0027172.20.208.1\u0027, os.name: \u0027Windows 10\u0027, os.arch: \u0027amd64\u0027, os.version: \u002710.0\u0027, java.version: \u002711.0.4\u0027\nDriver info: org.openqa.selenium.chrome.ChromeDriver\nCapabilities {acceptInsecureCerts: false, browserName: chrome, browserVersion: 95.0.4638.69, chrome: {chromedriverVersion: 95.0.4638.69 (6a1600ed572fe..., userDataDir: C:\\Users\\Sistemas\\AppData\\L...}, goog:chromeOptions: {debuggerAddress: localhost:52374}, javascriptEnabled: true, networkConnectionEnabled: false, pageLoadStrategy: normal, platform: WINDOWS, platformName: WINDOWS, proxy: Proxy(), setWindowRect: true, strictFileInteractability: false, timeouts: {implicit: 0, pageLoad: 300000, script: 30000}, unhandledPromptBehavior: dismiss and notify, webauthn:extension:credBlob: true, webauthn:extension:largeBlob: true, webauthn:virtualAuthenticators: true}\nSession ID: 406359d0b7d2bfbe3a11cd9b1ba20110\n*** Element info: {Using\u003dxpath, value\u003d//label[contains(@class,\u0027checkmark signup-consent__checkbox error\u0027)]}","stackTrace":[{"classLoaderName":"app","declaringClass":"co.com.dmvs.proyecto.task.StepComplete","methodName":"performAs","fileName":"StepComplete.java","lineNumber":20,"format":1},{"classLoaderName":"app","declaringClass":"co.com.dmvs.proyecto.stepdefinitions.ChourcairAcademyStepDefinitions","methodName":"youEnterTheDataRequestedForRegistration","fileName":"ChourcairAcademyStepDefinitions.java","lineNumber":27,"format":1},{"classLoaderName":"app","declaringClass":"cucumber.runner.Runner","methodName":"runPickle","fileName":"Runner.java","lineNumber":80,"format":1}]}}},"testFailureClassname":"net.thucydides.core.webdriver.exceptions.ElementShouldBeEnabledException","testFailureMessage":"Expected enabled element was not enabled","testFailureSummary":"FAILURE;net.thucydides.core.webdriver.exceptions.ElementShouldBeEnabledException;Expected enabled element was not enabled;StepComplete.java","projectKey":"","annotatedResult":"FAILURE","sessionId":"406359d0b7d2bfbe3a11cd9b1ba20110","driver":"chrome:mauricio","isManualTestingUpToDate":false,"manual":false,"testSource":"Cucumber","actors":[{"name":"Mauricio","can":["browse the web"]}],"result":"FAILURE"}